LICENSE
README.md
setup.py
mmmm_calculator/__init__.py
mmmm_calculator.egg-info/PKG-INFO
mmmm_calculator.egg-info/SOURCES.txt
mmmm_calculator.egg-info/dependency_links.txt
mmmm_calculator.egg-info/top_level.txt